bilibili_api_c/__init__.py
bilibili_api_c/base.py
bilibili_api_c/creative_center.py
bilibili_api_c/creative_center_data_types.py
bilibili_api_c/creative_center_response_types.py
bilibili_api_c/space.py
bilibili_api_c/space_data_types.py
bilibili_api_c-0.3.1.dist-info/METADATA
bilibili_api_c-0.3.1.dist-info/WHEEL
bilibili_api_c-0.3.1.dist-info/top_level.txt
bilibili_api_c-0.3.1.dist-info/RECORD
