Metadata-Version: 2.4
Name: bilibili_api_c
Version: 0.3.1
Requires-Python: >=3.10
Requires-Dist: requests
